qrmr/__init__.py
qrmr/qrmr.py
qrmr-0.4.2.dist-info/DESCRIPTION.rst
qrmr-0.4.2.dist-info/METADATA
qrmr-0.4.2.dist-info/RECORD
qrmr-0.4.2.dist-info/WHEEL
qrmr-0.4.2.dist-info/entry_points.txt
qrmr-0.4.2.dist-info/metadata.json
qrmr-0.4.2.dist-info/top_level.txt
