Metadata-Version: 2.0
Name: qrmr
Version: 0.4.2
Summary: Terminal login toolkit for Amazon Web Services (AWS) enforcing and simplifying use of Multi-Factor Authentication (MFA).
Home-page: https://gitlab.com/qrmr/qrmr
Author: Alexander L. de Goeij
Author-email: mail@aldg.nl
License: NO_LICENSE_YET
Keywords: cloud aws cli login mfa otp session token
Platform: UNKNOWN
Classifier: Development Status :: 3 - Alpha
Classifier: Environment :: Console
Classifier: Environment :: MacOS X
Classifier: Intended Audience :: Developers
Classifier: Intended Audience :: System Administrators
Classifier: Natural Language :: English
Classifier: Programming Language :: Python :: 3.6
Classifier: Programming Language :: Python :: 2.7
Classifier: Topic :: Software Development
Classifier: Topic :: Utilities
Requires-Dist: future
Requires-Dist: colorlog
Requires-Dist: boto3
Requires-Dist: configparser
Requires-Dist: requests
